{"header" :{
    "title":"menu_choix_niveau",
    "imagePath":"Assets/",
    "numberPlayerMin":2,
    "images":{"palourde":"/Entity/palourde.png",
                "retour_menu_button": "/Button/retour_menu_button.png",
                "escape_button": "/Button/escape_button.png"
            }},
"listeObject":[
            {"x":500, "y":200, "width":500, "height":500, "layer":2, "color":[0,0,120]},
            {"x" : 500 , "y": 200, "width" : 1200, "height" : 50, "layer":2, "image":"escape_button","type":"button", "name":"escape"},
            {"x" : 500 , "y": 500, "width" : 1200, "height" : 50, "layer":2, "image":"retour_menu_button","type":"button", "name":"retour_menu"}
        ]

} 